XICRA/__init__.py
XICRA/config/__init__.py
XICRA/config/extern_progs.py
XICRA/config/set_config.py
XICRA/config/R/R_dependencies.csv
XICRA/config/R/check_install_system.R
XICRA/config/python/python_requirement_summary.txt
XICRA/config/python/python_requirements.csv
XICRA/config/software/dependencies.csv
XICRA/config/software/installer.sh
XICRA/config/software/soft_dependencies.csv
XICRA/modules/__init__.py
XICRA/modules/biotype.py
XICRA/modules/citation.py
XICRA/modules/config.py
XICRA/modules/database.py
XICRA/modules/help_XICRA.py
XICRA/modules/join.py
XICRA/modules/map.py
XICRA/modules/miRNA.py
XICRA/modules/piRNA.py
XICRA/modules/prep.py
XICRA/modules/qc.py
XICRA/modules/tRNA.py
XICRA/modules/test.py
XICRA/modules/trim.py
XICRA/other_tools/__init__.py
XICRA/other_tools/plot_RNAbiotype_sum.R
XICRA/other_tools/tools.py
XICRA/scripts/BAMtoPILFER.py
XICRA/scripts/MINTMap_caller.py
XICRA/scripts/RNAbiotype.py
XICRA/scripts/STAR_caller.py
XICRA/scripts/__init__.py
XICRA/scripts/bedtools_caller.py
XICRA/scripts/cutadapt_caller.py
XICRA/scripts/fastqc_caller.py
XICRA/scripts/generate_DE.py
XICRA/scripts/get_length_distribution.py
XICRA/scripts/miraligner_caller.py
XICRA/scripts/mirtop_caller.py
XICRA/scripts/multiQC_report.py
XICRA/scripts/optimir_caller.py
XICRA/scripts/parse_genetype-bed.py
XICRA/scripts/pilfer_caller.py
XICRA/scripts/sRNAbench_caller.py
XICRA/scripts/samtools_caller.py
XICRA-1.6.0.data/scripts/XICRA
XICRA-1.6.0.dist-info/LICENSE
XICRA-1.6.0.dist-info/METADATA
XICRA-1.6.0.dist-info/WHEEL
XICRA-1.6.0.dist-info/top_level.txt
XICRA-1.6.0.dist-info/RECORD
