Metadata-Version: 2.1
Name: XICRA
Version: 1.6.0
Summary: Small RNAseq pipeline for paired-end reads
Home-page: https://github.com/HCGB-IGTP/XICRA/
Author: Jose F. Sanchez-Herrero
Author-email: jfbioinformatics@gmail.com
License: MIT License
Classifier: Programming Language :: Python :: 3
Classifier: License :: OSI Approved :: MIT License
Classifier: Operating System :: OS Independent
License-File: LICENSE
Requires-Dist: HCGB
Requires-Dist: biopython
Requires-Dist: cutadapt
Requires-Dist: future
Requires-Dist: gitdir
Requires-Dist: mirtop
Requires-Dist: multiqc
Requires-Dist: networkx
Requires-Dist: numpy
Requires-Dist: pandas
Requires-Dist: pybedtools
Requires-Dist: pysam
Requires-Dist: termcolor
